aws_sso_lite/__init__.py
aws_sso_lite/sso.py
aws_sso_lite/utils.py
aws_sso_lite/vendored/__init__.py
aws_sso_lite/vendored/botocore/__init__.py
aws_sso_lite/vendored/botocore/utils.py
aws_sso_lite-0.0.9.dist-info/licenses/LICENSE
aws_sso_lite-0.0.9.dist-info/METADATA
aws_sso_lite-0.0.9.dist-info/WHEEL
aws_sso_lite-0.0.9.dist-info/top_level.txt
aws_sso_lite-0.0.9.dist-info/RECORD
