Metadata-Version: 2.4
Name: aws-sso-lite
Version: 0.0.9
Summary: A lightweight package to do aws sso without aws cli
Home-page: https://github.com/kejun91/aws-sso-lite
Author: Jun Ke
Author-email: kejun91@gmail.com
Classifier: Programming Language :: Python :: 3
Classifier: License :: OSI Approved :: MIT License
Classifier: Operating System :: OS Independent
Requires-Python: >=3.6
License-File: LICENSE
Dynamic: author
Dynamic: author-email
Dynamic: classifier
Dynamic: description
Dynamic: description-content-type
Dynamic: home-page
Dynamic: license-file
Dynamic: requires-python
Dynamic: summary
